lab5/comparator_2bit_2.vhd
library IEEE;
use IEEE.STD_LOGIC_1164.ALL;
entity comparator_2bit_2 is
    Port ( A   : in  STD_LOGIC_VECTOR (1 downto 0);
           B   : in  STD_LOGIC_VECTOR (1 downto 0);
           greater : out STD_LOGIC;
           equal   : out STD_LOGIC;
           less    : out STD_LOGIC);
end comparator_2bit_2;
architecture Dataflow of comparator_2bit_2 is
begin
    greater <= '1' when (A > B) else '0';
    equal   <= '1' when (A = B) else '0';
    less    <= '1' when (A < B) else '0';
end Dataflow;

lab5/comparator_2bit_2_tb.vhd
library IEEE;
use IEEE.STD_LOGIC_1164.ALL;
use IEEE.NUMERIC_STD.ALL;

entity comparator_2bit_2_tb is
end comparator_2bit_2_tb;

architecture Behavioral of comparator_2bit_2_tb is
    component comparator_2bit_2
        Port ( A       : in  STD_LOGIC_VECTOR (1 downto 0);
               B       : in  STD_LOGIC_VECTOR (1 downto 0);
               greater : out STD_LOGIC;
               equal   : out STD_LOGIC;
               less    : out STD_LOGIC);
    end component;
    signal A_tb : STD_LOGIC_VECTOR(1 downto 0) := "00";
    signal B_tb : STD_LOGIC_VECTOR(1 downto 0) := "00";
    signal greater_tb : STD_LOGIC;
    signal equal_tb   : STD_LOGIC;
    signal less_tb    : STD_LOGIC;

begin

    uut: comparator_2bit_2 PORT MAP (
          A => A_tb,
          B => B_tb,
          greater => greater_tb,
          equal => equal_tb,
          less => less_tb
        );

    stim_proc: process
    begin		
        for i in 0 to 3 loop
            for j in 0 to 3 loop
                A_tb <= std_logic_vector(to_unsigned(i, 2));
                B_tb <= std_logic_vector(to_unsigned(j, 2));
                wait for 10 ns;
            end loop;
        end loop;
        wait;
    end process;

end Behavioral;

lab5/lab5/comparator2.vcd
$date
  Tue Jun 23 18:19:18 2026
$end
$version
  GHDL v0
$end
$timescale
  1 fs
$end
$scope module standard $end
$upscope $end
$scope module std_logic_1164 $end
$upscope $end
$scope module numeric_std $end
$upscope $end
$scope module comparator_2bit_2_tb $end
$var reg 2 ! a_tb[1:0] $end
$var reg 2 " b_tb[1:0] $end
$var reg 1 # greater_tb $end
$var reg 1 $ equal_tb $end
$var reg 1 % less_tb $end
$scope module uut $end
$var reg 2 & a[1:0] $end
$var reg 2 ' b[1:0] $end
$var reg 1 ( greater $end
$var reg 1 ) equal $end
$var reg 1 * less $end
$upscope $end
$upscope $end
$enddefinitions $end
#0
b00 !
b00 "
0#
1$
0%
b00 &
b00 '
0(
1)
0*
#10000000
b01 "
0$
1%
b01 '
0)
1*
#20000000
b10 "
b10 '
#30000000
b11 "
b11 '
#40000000
b01 !
b00 "
1#
0%
b01 &
b00 '
1(
0*
#50000000
b01 "
0#
1$
b01 '
0(
1)
#60000000
b10 "
0$
1%
b10 '
0)
1*
#70000000
b11 "
b11 '
#80000000
b10 !
b00 "
1#
0%
b10 &
b00 '
1(
0*
#90000000
b01 "
b01 '
#100000000
b10 "
0#
1$
b10 '
0(
1)
#110000000
b11 "
0$
1%
b11 '
0)
1*
#120000000
b11 !
b00 "
1#
0%
b11 &
b00 '
1(
0*
#130000000
b01 "
b01 '
#140000000
b10 "
b10 '
#150000000
b11 "
0#
1$
b11 '
0(
1)
