lab5/lab5/comparator_2bit_2.vhd
library IEEE;
use IEEE.STD_LOGIC_1164.ALL;

entity comparator_2bit_2  is
    port(
        A  : in std_logic_vector(1 downto 0); -- A1A0
        B  : in std_logic_vector(1 downto 0); -- B1B0
        EQ : out std_logic;
        GT : out std_logic;
        LT : out std_logic
    );
end entity comparator_2bit_2 ;

architecture Behavioral of comparator_2bit_2 is
begin
    EQ <= (not(A(1) xor B(1))) and (not(A(0) xor B(0)));
    GT <= (A(1) and not B(1)) or ((not(A(1) xor B(1))) and (A(0) and not B(0)));
    LT <= ((not A(1)) and B(1)) or ((not(A(1) xor B(1))) and ((not A(0)) and B(0)));
end architecture Behavioral;

lab5/lab5/comparator_2bit_2_tb.vhd
library IEEE;
use IEEE.STD_LOGIC_1164.ALL;
use IEEE.NUMERIC_STD.ALL;

entity comparator_2bit_2_tb is
end entity comparator_2bit_2_tb;

architecture Simulation of comparator_2bit_2_tb is
    signal A, B : std_logic_vector(1 downto 0);
    signal EQ, GT, LT : std_logic;
begin

    DUT: entity work.comparator_2bit_2
        port map(A => A, B => B, EQ => EQ, GT => GT, LT => LT);

    STIMULUS: process
    begin
       
        for i in 0 to 3 loop
            for j in 0 to 3 loop
                A <= std_logic_vector(to_unsigned(i, 2));
                B <= std_logic_vector(to_unsigned(j, 2));
                wait for 10 ns;
            end loop;
        end loop;

        wait;
    end process;
end architecture Simulation;

lab5/lab5/comparator.vcd
$date
  Fri Jul 10 16:23:24 2026
$end
$version
  GHDL v0
$end
$timescale
  1 fs
$end
$scope module standard $end
$upscope $end
$scope module std_logic_1164 $end
$upscope $end
$scope module numeric_std $end
$upscope $end
$scope module comparator_2bit_2_tb $end
$var reg 2 ! a[1:0] $end
$var reg 2 " b[1:0] $end
$var reg 1 # eq $end
$var reg 1 $ gt $end
$var reg 1 % lt $end
$scope module dut $end
$var reg 2 & a[1:0] $end
$var reg 2 ' b[1:0] $end
$var reg 1 ( eq $end
$var reg 1 ) gt $end
$var reg 1 * lt $end
$upscope $end
$upscope $end
$enddefinitions $end
#0
b00 !
b00 "
1#
0$
0%
b00 &
b00 '
1(
0)
0*
#10000000
b01 "
0#
1%
b01 '
0(
1*
#20000000
b10 "
b10 '
#30000000
b11 "
b11 '
#40000000
b01 !
b00 "
1$
0%
b01 &
b00 '
1)
0*
#50000000
b01 "
1#
0$
b01 '
1(
0)
#60000000
b10 "
0#
1%
b10 '
0(
1*
#70000000
b11 "
b11 '
#80000000
b10 !
b00 "
1$
0%
b10 &
b00 '
1)
0*
#90000000
b01 "
b01 '
#100000000
b10 "
1#
0$
b10 '
1(
0)
#110000000
b11 "
0#
1%
b11 '
0(
1*
#120000000
b11 !
b00 "
1$
0%
b11 &
b00 '
1)
0*
#130000000
b01 "
b01 '
#140000000
b10 "
b10 '
#150000000
b11 "
1#
0$
b11 '
1(
0)
